selfpowerdecomposer/__init__.py
selfpowerdecomposer/setup.py
selfpowerdecomposer/test_local_install.py
selfpowerdecomposer/examples/basic_usage.py
selfpowerdecomposer/examples/secure_example.py
selfpowerdecomposer/selfpowerdecomposer/__init__.py
selfpowerdecomposer/selfpowerdecomposer/core.py
selfpowerdecomposer/tests/__init__.py
selfpowerdecomposer/tests/test_selfpowerdecomposer.py
selfpowerdecomposer-0.1.2.dist-info/LICENSE
selfpowerdecomposer-0.1.2.dist-info/METADATA
selfpowerdecomposer-0.1.2.dist-info/WHEEL
selfpowerdecomposer-0.1.2.dist-info/top_level.txt
selfpowerdecomposer-0.1.2.dist-info/RECORD
