Metadata-Version: 2.2
Name: selfpowerdecomposer
Version: 0.1.2
Summary: Large integer compression and secure encoding using self-power decomposition
Author-email: SelfPower Team <lordrichado@gmail.com>
License: MIT
Project-URL: Homepage, https://github.com/joirichi/selfpowerdecomposer
Project-URL: Bug Tracker, https://github.com/joirichi/selfpowerdecomposer/issues
Classifier: Programming Language :: Python :: 3
Classifier: License :: OSI Approved :: MIT License
Classifier: Operating System :: OS Independent
Classifier: Topic :: Scientific/Engineering :: Mathematics
Classifier: Topic :: System :: Archiving :: Compression
Classifier: Topic :: Security :: Cryptography
Requires-Python: >=3.6
License-File: LICENSE
Requires-Dist: gmpy2>=2.0.8
Requires-Dist: numpy>=1.19.0
Requires-Dist: matplotlib>=3.3.0
